<annotation>
  <folder>red bull</folder>
  <filename>img000324</filename>
  <path>LogoDataset\red bull\img000324.jpg</path>
  <source>
    <database>Unknown</database>
  </source>
  <size>
    <width>450</width>
    <height>302</height>
    <depth>3</depth>
  </size>
  <segmented>0</segmented>
  <object>
    <name>RedBull-logo</name>
    <pose>Unspecified</pose>
    <truncated>0</truncated>
    <difficult>0</difficult>
    <bndbox>
      <xmin>242</xmin>
      <ymin>170</ymin>
      <xmax>376</xmax>
      <ymax>275</ymax>
    </bndbox>
  </object>
  <object>
    <name>RedBull</name>
    <pose>Unspecified</pose>
    <truncated>0</truncated>
    <difficult>0</difficult>
    <bndbox>
      <xmin>245</xmin>
      <ymin>268</ymin>
      <xmax>286</xmax>
      <ymax>294</ymax>
    </bndbox>
  </object>
  <object>
    <name>RedBull</name>
    <pose>Unspecified</pose>
    <truncated>0</truncated>
    <difficult>0</difficult>
    <bndbox>
      <xmin>3</xmin>
      <ymin>215</ymin>
      <xmax>81</xmax>
      <ymax>253</ymax>
    </bndbox>
  </object>
  <object>
    <name>RedBull-logo</name>
    <pose>Unspecified</pose>
    <truncated>0</truncated>
    <difficult>0</difficult>
    <bndbox>
      <xmin>34</xmin>
      <ymin>204</ymin>
      <xmax>101</xmax>
      <ymax>229</ymax>
    </bndbox>
  </object>
</annotation>
