<annotation>
  <folder>red bull</folder>
  <filename>img000465</filename>
  <path>LogoDataset\red bull\img000465.jpg</path>
  <source>
    <database>Unknown</database>
  </source>
  <size>
    <width>1600</width>
    <height>1200</height>
    <depth>3</depth>
  </size>
  <segmented>0</segmented>
  <object>
    <name>TOTAL</name>
    <pose>Unspecified</pose>
    <truncated>0</truncated>
    <difficult>0</difficult>
    <bndbox>
      <xmin>268</xmin>
      <ymin>460</ymin>
      <xmax>537</xmax>
      <ymax>524</ymax>
    </bndbox>
  </object>
  <object>
    <name>MICHELIN</name>
    <pose>Unspecified</pose>
    <truncated>0</truncated>
    <difficult>0</difficult>
    <bndbox>
      <xmin>738</xmin>
      <ymin>536</ymin>
      <xmax>852</xmax>
      <ymax>569</ymax>
    </bndbox>
  </object>
  <object>
    <name>RedBull-logo</name>
    <pose>Unspecified</pose>
    <truncated>0</truncated>
    <difficult>0</difficult>
    <bndbox>
      <xmin>299</xmin>
      <ymin>380</ymin>
      <xmax>644</xmax>
      <ymax>445</ymax>
    </bndbox>
  </object>
  <object>
    <name>MICHELIN</name>
    <pose>Unspecified</pose>
    <truncated>0</truncated>
    <difficult>0</difficult>
    <bndbox>
      <xmin>984</xmin>
      <ymin>459</ymin>
      <xmax>1113</xmax>
      <ymax>587</ymax>
    </bndbox>
  </object>
  <object>
    <name>RedBull</name>
    <pose>Unspecified</pose>
    <truncated>0</truncated>
    <difficult>0</difficult>
    <bndbox>
      <xmin>1283</xmin>
      <ymin>411</ymin>
      <xmax>1430</xmax>
      <ymax>504</ymax>
    </bndbox>
  </object>
  <object>
    <name>RedBull-logo</name>
    <pose>Unspecified</pose>
    <truncated>0</truncated>
    <difficult>0</difficult>
    <bndbox>
      <xmin>1150</xmin>
      <ymin>441</ymin>
      <xmax>1280</xmax>
      <ymax>634</ymax>
    </bndbox>
  </object>
</annotation>
