<annotation>
  <folder>reebok</folder>
  <filename>img000049</filename>
  <path>LogoDataset\reebok\img000049.jpg</path>
  <source>
    <database>Unknown</database>
  </source>
  <size>
    <width>1500</width>
    <height>1000</height>
    <depth>3</depth>
  </size>
  <segmented>0</segmented>
  <object>
    <name>Reebok</name>
    <pose>Unspecified</pose>
    <truncated>0</truncated>
    <difficult>0</difficult>
    <bndbox>
      <xmin>742</xmin>
      <ymin>371</ymin>
      <xmax>846</xmax>
      <ymax>433</ymax>
    </bndbox>
  </object>
  <object>
    <name>Reebok-logo</name>
    <pose>Unspecified</pose>
    <truncated>0</truncated>
    <difficult>0</difficult>
    <bndbox>
      <xmin>847</xmin>
      <ymin>384</ymin>
      <xmax>875</xmax>
      <ymax>438</ymax>
    </bndbox>
  </object>
  <object>
    <name>Reebok-logo</name>
    <pose>Unspecified</pose>
    <truncated>0</truncated>
    <difficult>0</difficult>
    <bndbox>
      <xmin>1127</xmin>
      <ymin>459</ymin>
      <xmax>1164</xmax>
      <ymax>487</ymax>
    </bndbox>
  </object>
  <object>
    <name>Reebok</name>
    <pose>Unspecified</pose>
    <truncated>0</truncated>
    <difficult>0</difficult>
    <bndbox>
      <xmin>1121</xmin>
      <ymin>483</ymin>
      <xmax>1167</xmax>
      <ymax>496</ymax>
    </bndbox>
  </object>
  <object>
    <name>Reebok</name>
    <pose>Unspecified</pose>
    <truncated>0</truncated>
    <difficult>0</difficult>
    <bndbox>
      <xmin>200</xmin>
      <ymin>138</ymin>
      <xmax>380</xmax>
      <ymax>215</ymax>
    </bndbox>
  </object>
  <object>
    <name>Reebok</name>
    <pose>Unspecified</pose>
    <truncated>0</truncated>
    <difficult>0</difficult>
    <bndbox>
      <xmin>371</xmin>
      <ymin>620</ymin>
      <xmax>456</xmax>
      <ymax>648</ymax>
    </bndbox>
  </object>
</annotation>
