<annotation>
  <folder>bem wireless</folder>
  <filename>img000020</filename>
  <path>LogoDataset\bem wireless\img000020.jpg</path>
  <source>
    <database>Unknown</database>
  </source>
  <size>
    <width>1200</width>
    <height>1200</height>
    <depth>3</depth>
  </size>
  <segmented>0</segmented>
  <object>
    <name>bem</name>
    <pose>Unspecified</pose>
    <truncated>0</truncated>
    <difficult>0</difficult>
    <bndbox>
      <xmin>372</xmin>
      <ymin>425</ymin>
      <xmax>406</xmax>
      <ymax>592</ymax>
    </bndbox>
  </object>
  <object>
    <name>bem</name>
    <pose>Unspecified</pose>
    <truncated>0</truncated>
    <difficult>0</difficult>
    <bndbox>
      <xmin>242</xmin>
      <ymin>250</ymin>
      <xmax>425</xmax>
      <ymax>293</ymax>
    </bndbox>
  </object>
  <object>
    <name>bem</name>
    <pose>Unspecified</pose>
    <truncated>0</truncated>
    <difficult>0</difficult>
    <bndbox>
      <xmin>645</xmin>
      <ymin>446</ymin>
      <xmax>720</xmax>
      <ymax>498</ymax>
    </bndbox>
  </object>
</annotation>
