<annotation>
  <folder>heineken</folder>
  <filename>img000351</filename>
  <path>LogoDataset\heineken\img000351.jpg</path>
  <source>
    <database>Unknown</database>
  </source>
  <size>
    <width>620</width>
    <height>350</height>
    <depth>3</depth>
  </size>
  <segmented>0</segmented>
  <object>
    <name>Heineken</name>
    <pose>Unspecified</pose>
    <truncated>0</truncated>
    <difficult>0</difficult>
    <bndbox>
      <xmin>269</xmin>
      <ymin>91</ymin>
      <xmax>337</xmax>
      <ymax>105</ymax>
    </bndbox>
  </object>
</annotation>
