<annotation>
  <folder>heineken</folder>
  <filename>img000039</filename>
  <path>LogoDataset\heineken\img000039.jpg</path>
  <source>
    <database>Unknown</database>
  </source>
  <size>
    <width>886</width>
    <height>591</height>
    <depth>3</depth>
  </size>
  <segmented>0</segmented>
  <object>
    <name>Heineken</name>
    <pose>Unspecified</pose>
    <truncated>0</truncated>
    <difficult>0</difficult>
    <bndbox>
      <xmin>357</xmin>
      <ymin>80</ymin>
      <xmax>541</xmax>
      <ymax>190</ymax>
    </bndbox>
  </object>
</annotation>
