<annotation>
  <folder>Samsung</folder>
  <filename>img000007</filename>
  <path>LogoDataset\Samsung\img000007.jpg</path>
  <source>
    <database>Unknown</database>
  </source>
  <size>
    <width>600</width>
    <height>315</height>
    <depth>3</depth>
  </size>
  <segmented>0</segmented>
  <object>
    <name>samsung</name>
    <pose>Unspecified</pose>
    <truncated>0</truncated>
    <difficult>0</difficult>
    <bndbox>
      <xmin>416</xmin>
      <ymin>196</ymin>
      <xmax>585</xmax>
      <ymax>315</ymax>
    </bndbox>
  </object>
</annotation>
