<annotation>
  <folder>Walmart</folder>
  <filename>img000091</filename>
  <path>LogoDataset\Walmart\img000091.jpg</path>
  <source>
    <database>Unknown</database>
  </source>
  <size>
    <width>350</width>
    <height>287</height>
    <depth>3</depth>
  </size>
  <segmented>0</segmented>
  <object>
    <name>walmart</name>
    <pose>Unspecified</pose>
    <truncated>0</truncated>
    <difficult>0</difficult>
    <bndbox>
      <xmin>5</xmin>
      <ymin>7</ymin>
      <xmax>332</xmax>
      <ymax>123</ymax>
    </bndbox>
  </object>
  <object>
    <name>pepsi-logo</name>
    <pose>Unspecified</pose>
    <truncated>0</truncated>
    <difficult>0</difficult>
    <bndbox>
      <xmin>252</xmin>
      <ymin>208</ymin>
      <xmax>265</xmax>
      <ymax>225</ymax>
    </bndbox>
  </object>
</annotation>
