<annotation>
  <folder>intel</folder>
  <filename>img000070</filename>
  <path>LogoDataset\intel\img000070.jpg</path>
  <source>
    <database>Unknown</database>
  </source>
  <size>
    <width>401</width>
    <height>350</height>
    <depth>3</depth>
  </size>
  <segmented>0</segmented>
  <object>
    <name>DELL</name>
    <pose>Unspecified</pose>
    <truncated>0</truncated>
    <difficult>0</difficult>
    <bndbox>
      <xmin>219</xmin>
      <ymin>197</ymin>
      <xmax>258</xmax>
      <ymax>239</ymax>
    </bndbox>
  </object>
</annotation>
