<annotation>
  <folder>burger king</folder>
  <filename>img000386</filename>
  <path>LogoDataset\burger king\img000386.jpg</path>
  <source>
    <database>Unknown</database>
  </source>
  <size>
    <width>640</width>
    <height>446</height>
    <depth>3</depth>
  </size>
  <segmented>0</segmented>
  <object>
    <name>burgerking-schriftzug</name>
    <pose>Unspecified</pose>
    <truncated>0</truncated>
    <difficult>0</difficult>
    <bndbox>
      <xmin>35</xmin>
      <ymin>80</ymin>
      <xmax>592</xmax>
      <ymax>151</ymax>
    </bndbox>
  </object>
</annotation>
