<annotation>
  <folder>boeing</folder>
  <filename>img000031</filename>
  <path>LogoDataset\boeing\img000031.jpg</path>
  <source>
    <database>Unknown</database>
  </source>
  <size>
    <width>3300</width>
    <height>2475</height>
    <depth>3</depth>
  </size>
  <segmented>0</segmented>
  <object>
    <name>boeing-schriftzug</name>
    <pose>Unspecified</pose>
    <truncated>0</truncated>
    <difficult>0</difficult>
    <bndbox>
      <xmin>1895</xmin>
      <ymin>1647</ymin>
      <xmax>2168</xmax>
      <ymax>1800</ymax>
    </bndbox>
  </object>
  <object>
    <name>boing-logo</name>
    <pose>Unspecified</pose>
    <truncated>0</truncated>
    <difficult>0</difficult>
    <bndbox>
      <xmin>1811</xmin>
      <ymin>1607</ymin>
      <xmax>1915</xmax>
      <ymax>1750</ymax>
    </bndbox>
  </object>
</annotation>
