<annotation>
  <folder>bosch</folder>
  <filename>img000342</filename>
  <path>LogoDataset\bosch\img000342.jpg</path>
  <source>
    <database>Unknown</database>
  </source>
  <size>
    <width>750</width>
    <height>500</height>
    <depth>3</depth>
  </size>
  <segmented>0</segmented>
  <object>
    <name>bosch-schriftzug</name>
    <pose>Unspecified</pose>
    <truncated>0</truncated>
    <difficult>0</difficult>
    <bndbox>
      <xmin>585</xmin>
      <ymin>135</ymin>
      <xmax>643</xmax>
      <ymax>172</ymax>
    </bndbox>
  </object>
  <object>
    <name>bosch-schriftzug</name>
    <pose>Unspecified</pose>
    <truncated>0</truncated>
    <difficult>0</difficult>
    <bndbox>
      <xmin>214</xmin>
      <ymin>195</ymin>
      <xmax>245</xmax>
      <ymax>208</ymax>
    </bndbox>
  </object>
  <object>
    <name>bosch-schriftzug</name>
    <pose>Unspecified</pose>
    <truncated>0</truncated>
    <difficult>0</difficult>
    <bndbox>
      <xmin>421</xmin>
      <ymin>248</ymin>
      <xmax>439</xmax>
      <ymax>259</ymax>
    </bndbox>
  </object>
  <object>
    <name>bosch-schriftzug</name>
    <pose>Unspecified</pose>
    <truncated>0</truncated>
    <difficult>0</difficult>
    <bndbox>
      <xmin>305</xmin>
      <ymin>191</ymin>
      <xmax>336</xmax>
      <ymax>206</ymax>
    </bndbox>
  </object>
  <object>
    <name>bosch-logo</name>
    <pose>Unspecified</pose>
    <truncated>0</truncated>
    <difficult>0</difficult>
    <bndbox>
      <xmin>607</xmin>
      <ymin>192</ymin>
      <xmax>623</xmax>
      <ymax>218</ymax>
    </bndbox>
  </object>
</annotation>
