<annotation>
  <folder>huawei</folder>
  <filename>img000227</filename>
  <path>LogoDataset\huawei\img000227.jpg</path>
  <source>
    <database>Unknown</database>
  </source>
  <size>
    <width>574</width>
    <height>358</height>
    <depth>3</depth>
  </size>
  <segmented>0</segmented>
  <object>
    <name>huawei</name>
    <pose>Unspecified</pose>
    <truncated>0</truncated>
    <difficult>0</difficult>
    <bndbox>
      <xmin>54</xmin>
      <ymin>186</ymin>
      <xmax>261</xmax>
      <ymax>230</ymax>
    </bndbox>
  </object>
  <object>
    <name>huawei-logo</name>
    <pose>Unspecified</pose>
    <truncated>0</truncated>
    <difficult>0</difficult>
    <bndbox>
      <xmin>42</xmin>
      <ymin>7</ymin>
      <xmax>257</xmax>
      <ymax>170</ymax>
    </bndbox>
  </object>
</annotation>
