<annotation>
  <folder>philips</folder>
  <filename>img000068</filename>
  <path>LogoDataset\philips\img000068.jpg</path>
  <source>
    <database>Unknown</database>
  </source>
  <size>
    <width>670</width>
    <height>436</height>
    <depth>3</depth>
  </size>
  <segmented>0</segmented>
  <object>
    <name>philips</name>
    <pose>Unspecified</pose>
    <truncated>0</truncated>
    <difficult>0</difficult>
    <bndbox>
      <xmin>286</xmin>
      <ymin>25</ymin>
      <xmax>450</xmax>
      <ymax>89</ymax>
    </bndbox>
  </object>
  <object>
    <name>philips</name>
    <pose>Unspecified</pose>
    <truncated>0</truncated>
    <difficult>0</difficult>
    <bndbox>
      <xmin>85</xmin>
      <ymin>70</ymin>
      <xmax>134</xmax>
      <ymax>92</ymax>
    </bndbox>
  </object>
  <object>
    <name>philips</name>
    <pose>Unspecified</pose>
    <truncated>0</truncated>
    <difficult>0</difficult>
    <bndbox>
      <xmin>493</xmin>
      <ymin>277</ymin>
      <xmax>529</xmax>
      <ymax>289</ymax>
    </bndbox>
  </object>
</annotation>
