<annotation>
  <folder>santander</folder>
  <filename>img000044</filename>
  <path>LogoDataset\santander\img000044.jpg</path>
  <source>
    <database>Unknown</database>
  </source>
  <size>
    <width>5115</width>
    <height>3837</height>
    <depth>3</depth>
  </size>
  <segmented>0</segmented>
  <object>
    <name>Santander-logo</name>
    <pose>Unspecified</pose>
    <truncated>0</truncated>
    <difficult>0</difficult>
    <bndbox>
      <xmin>3316</xmin>
      <ymin>275</ymin>
      <xmax>3591</xmax>
      <ymax>557</ymax>
    </bndbox>
  </object>
  <object>
    <name>Santander</name>
    <pose>Unspecified</pose>
    <truncated>0</truncated>
    <difficult>0</difficult>
    <bndbox>
      <xmin>3648</xmin>
      <ymin>339</ymin>
      <xmax>4594</xmax>
      <ymax>629</ymax>
    </bndbox>
  </object>
  <object>
    <name>Santander-logo</name>
    <pose>Unspecified</pose>
    <truncated>0</truncated>
    <difficult>0</difficult>
    <bndbox>
      <xmin>1159</xmin>
      <ymin>111</ymin>
      <xmax>1541</xmax>
      <ymax>429</ymax>
    </bndbox>
  </object>
  <object>
    <name>Santander-logo</name>
    <pose>Unspecified</pose>
    <truncated>0</truncated>
    <difficult>0</difficult>
    <bndbox>
      <xmin>3469</xmin>
      <ymin>1136</ymin>
      <xmax>3598</xmax>
      <ymax>1257</ymax>
    </bndbox>
  </object>
</annotation>
