<annotation>
  <folder>chanel</folder>
  <filename>img000038</filename>
  <path>LogoDataset\chanel\img000038.jpg</path>
  <source>
    <database>Unknown</database>
  </source>
  <size>
    <width>1024</width>
    <height>768</height>
    <depth>3</depth>
  </size>
  <segmented>0</segmented>
  <object>
    <name>chanel</name>
    <pose>Unspecified</pose>
    <truncated>0</truncated>
    <difficult>0</difficult>
    <bndbox>
      <xmin>400</xmin>
      <ymin>371</ymin>
      <xmax>583</xmax>
      <ymax>406</ymax>
    </bndbox>
  </object>
  <object>
    <name>chanel</name>
    <pose>Unspecified</pose>
    <truncated>0</truncated>
    <difficult>0</difficult>
    <bndbox>
      <xmin>570</xmin>
      <ymin>480</ymin>
      <xmax>581</xmax>
      <ymax>531</ymax>
    </bndbox>
  </object>
  <object>
    <name>chanel</name>
    <pose>Unspecified</pose>
    <truncated>0</truncated>
    <difficult>0</difficult>
    <bndbox>
      <xmin>615</xmin>
      <ymin>537</ymin>
      <xmax>663</xmax>
      <ymax>547</ymax>
    </bndbox>
  </object>
</annotation>
