<annotation>
  <folder>volkswagen</folder>
  <filename>img000796</filename>
  <path>LogoDataset\volkswagen\img000796.jpg</path>
  <source>
    <database>Unknown</database>
  </source>
  <size>
    <width>400</width>
    <height>300</height>
    <depth>3</depth>
  </size>
  <segmented>0</segmented>
  <object>
    <name>VW</name>
    <pose>Unspecified</pose>
    <truncated>0</truncated>
    <difficult>0</difficult>
    <bndbox>
      <xmin>92</xmin>
      <ymin>145</ymin>
      <xmax>117</xmax>
      <ymax>174</ymax>
    </bndbox>
  </object>
  <object>
    <name>Audi</name>
    <pose>Unspecified</pose>
    <truncated>0</truncated>
    <difficult>0</difficult>
    <bndbox>
      <xmin>8</xmin>
      <ymin>264</ymin>
      <xmax>70</xmax>
      <ymax>287</ymax>
    </bndbox>
  </object>
  <object>
    <name>Audi-schrift</name>
    <pose>Unspecified</pose>
    <truncated>0</truncated>
    <difficult>0</difficult>
    <bndbox>
      <xmin>80</xmin>
      <ymin>261</ymin>
      <xmax>117</xmax>
      <ymax>274</ymax>
    </bndbox>
  </object>
  <object>
    <name>VW-schrift</name>
    <pose>Unspecified</pose>
    <truncated>0</truncated>
    <difficult>0</difficult>
    <bndbox>
      <xmin>167</xmin>
      <ymin>276</ymin>
      <xmax>231</xmax>
      <ymax>288</ymax>
    </bndbox>
  </object>
</annotation>
