<annotation>
  <folder>volkswagen</folder>
  <filename>img000392</filename>
  <path>LogoDataset\volkswagen\img000392.jpg</path>
  <source>
    <database>Unknown</database>
  </source>
  <size>
    <width>630</width>
    <height>420</height>
    <depth>3</depth>
  </size>
  <segmented>0</segmented>
  <object>
    <name>VW</name>
    <pose>Unspecified</pose>
    <truncated>0</truncated>
    <difficult>0</difficult>
    <bndbox>
      <xmin>291</xmin>
      <ymin>204</ymin>
      <xmax>338</xmax>
      <ymax>244</ymax>
    </bndbox>
  </object>
</annotation>
