<annotation>
  <folder>volkswagen</folder>
  <filename>img000527</filename>
  <path>LogoDataset\volkswagen\img000527.jpg</path>
  <source>
    <database>Unknown</database>
  </source>
  <size>
    <width>960</width>
    <height>485</height>
    <depth>3</depth>
  </size>
  <segmented>0</segmented>
  <object>
    <name>VW</name>
    <pose>Unspecified</pose>
    <truncated>0</truncated>
    <difficult>0</difficult>
    <bndbox>
      <xmin>684</xmin>
      <ymin>239</ymin>
      <xmax>703</xmax>
      <ymax>263</ymax>
    </bndbox>
  </object>
</annotation>
