<annotation>
  <folder>volkswagen</folder>
  <filename>img000157</filename>
  <path>LogoDataset\volkswagen\img000157.jpg</path>
  <source>
    <database>Unknown</database>
  </source>
  <size>
    <width>664</width>
    <height>443</height>
    <depth>3</depth>
  </size>
  <segmented>0</segmented>
  <object>
    <name>VW</name>
    <pose>Unspecified</pose>
    <truncated>0</truncated>
    <difficult>0</difficult>
    <bndbox>
      <xmin>521</xmin>
      <ymin>265</ymin>
      <xmax>541</xmax>
      <ymax>283</ymax>
    </bndbox>
  </object>
  <object>
    <name>VW-teilsichtbar</name>
    <pose>Unspecified</pose>
    <truncated>0</truncated>
    <difficult>0</difficult>
    <bndbox>
      <xmin>97</xmin>
      <ymin>253</ymin>
      <xmax>112</xmax>
      <ymax>265</ymax>
    </bndbox>
  </object>
  <object>
    <name>VW-schrift</name>
    <pose>Unspecified</pose>
    <truncated>0</truncated>
    <difficult>0</difficult>
    <bndbox>
      <xmin>136</xmin>
      <ymin>96</ymin>
      <xmax>303</xmax>
      <ymax>128</ymax>
    </bndbox>
  </object>
</annotation>
