<annotation>
  <folder>colgate</folder>
  <filename>img000021</filename>
  <path>LogoDataset\colgate\img000021.jpg</path>
  <source>
    <database>Unknown</database>
  </source>
  <size>
    <width>1600</width>
    <height>954</height>
    <depth>3</depth>
  </size>
  <segmented>0</segmented>
  <object>
    <name>colgate</name>
    <pose>Unspecified</pose>
    <truncated>0</truncated>
    <difficult>0</difficult>
    <bndbox>
      <xmin>444</xmin>
      <ymin>193</ymin>
      <xmax>1001</xmax>
      <ymax>333</ymax>
    </bndbox>
  </object>
  <object>
    <name>colgate</name>
    <pose>Unspecified</pose>
    <truncated>0</truncated>
    <difficult>0</difficult>
    <bndbox>
      <xmin>165</xmin>
      <ymin>565</ymin>
      <xmax>867</xmax>
      <ymax>728</ymax>
    </bndbox>
  </object>
  <object>
    <name>colgate</name>
    <pose>Unspecified</pose>
    <truncated>0</truncated>
    <difficult>0</difficult>
    <bndbox>
      <xmin>67</xmin>
      <ymin>559</ymin>
      <xmax>92</xmax>
      <ymax>853</ymax>
    </bndbox>
  </object>
</annotation>
