<annotation>
  <folder>colgate</folder>
  <filename>img000057</filename>
  <path>LogoDataset\colgate\img000057.jpg</path>
  <source>
    <database>Unknown</database>
  </source>
  <size>
    <width>500</width>
    <height>500</height>
    <depth>3</depth>
  </size>
  <segmented>0</segmented>
  <object>
    <name>colgate</name>
    <pose>Unspecified</pose>
    <truncated>0</truncated>
    <difficult>0</difficult>
    <bndbox>
      <xmin>12</xmin>
      <ymin>206</ymin>
      <xmax>233</xmax>
      <ymax>256</ymax>
    </bndbox>
  </object>
  <object>
    <name>colgate</name>
    <pose>Unspecified</pose>
    <truncated>0</truncated>
    <difficult>0</difficult>
    <bndbox>
      <xmin>36</xmin>
      <ymin>172</ymin>
      <xmax>252</xmax>
      <ymax>185</ymax>
    </bndbox>
  </object>
  <object>
    <name>colgate</name>
    <pose>Unspecified</pose>
    <truncated>0</truncated>
    <difficult>0</difficult>
    <bndbox>
      <xmin>478</xmin>
      <ymin>209</ymin>
      <xmax>486</xmax>
      <ymax>310</ymax>
    </bndbox>
  </object>
</annotation>
