<annotation>
  <folder>shell</folder>
  <filename>img000019</filename>
  <path>LogoDataset\shell\img000019.jpg</path>
  <source>
    <database>Unknown</database>
  </source>
  <size>
    <width>864</width>
    <height>1390</height>
    <depth>3</depth>
  </size>
  <segmented>0</segmented>
  <object>
    <name>shell-logo</name>
    <pose>Unspecified</pose>
    <truncated>0</truncated>
    <difficult>0</difficult>
    <bndbox>
      <xmin>258</xmin>
      <ymin>425</ymin>
      <xmax>391</xmax>
      <ymax>580</ymax>
    </bndbox>
  </object>
  <object>
    <name>shell-schrift-teilsichtbar</name>
    <pose>Unspecified</pose>
    <truncated>0</truncated>
    <difficult>0</difficult>
    <bndbox>
      <xmin>757</xmin>
      <ymin>769</ymin>
      <xmax>768</xmax>
      <ymax>790</ymax>
    </bndbox>
  </object>
  <object>
    <name>shell-schrift</name>
    <pose>Unspecified</pose>
    <truncated>0</truncated>
    <difficult>0</difficult>
    <bndbox>
      <xmin>291</xmin>
      <ymin>834</ymin>
      <xmax>313</xmax>
      <ymax>845</ymax>
    </bndbox>
  </object>
  <object>
    <name>shell-schrift-teilsichtbar</name>
    <pose>Unspecified</pose>
    <truncated>0</truncated>
    <difficult>0</difficult>
    <bndbox>
      <xmin>292</xmin>
      <ymin>767</ymin>
      <xmax>310</xmax>
      <ymax>778</ymax>
    </bndbox>
  </object>
</annotation>
