<annotation>
  <folder>honda</folder>
  <filename>img000180</filename>
  <path>LogoDataset\honda\img000180.jpg</path>
  <source>
    <database>Unknown</database>
  </source>
  <size>
    <width>404</width>
    <height>269</height>
    <depth>3</depth>
  </size>
  <segmented>0</segmented>
  <object>
    <name>honda-logo</name>
    <pose>Unspecified</pose>
    <truncated>0</truncated>
    <difficult>0</difficult>
    <bndbox>
      <xmin>76</xmin>
      <ymin>117</ymin>
      <xmax>91</xmax>
      <ymax>130</ymax>
    </bndbox>
  </object>
  <object>
    <name>mazda</name>
    <pose>Unspecified</pose>
    <truncated>0</truncated>
    <difficult>0</difficult>
    <bndbox>
      <xmin>17</xmin>
      <ymin>257</ymin>
      <xmax>82</xmax>
      <ymax>269</ymax>
    </bndbox>
  </object>
  <object>
    <name>ford</name>
    <pose>Unspecified</pose>
    <truncated>0</truncated>
    <difficult>0</difficult>
    <bndbox>
      <xmin>157</xmin>
      <ymin>257</ymin>
      <xmax>190</xmax>
      <ymax>269</ymax>
    </bndbox>
  </object>
  <object>
    <name>suzuki</name>
    <pose>Unspecified</pose>
    <truncated>0</truncated>
    <difficult>0</difficult>
    <bndbox>
      <xmin>88</xmin>
      <ymin>258</ymin>
      <xmax>150</xmax>
      <ymax>269</ymax>
    </bndbox>
  </object>
</annotation>
