<annotation>
  <folder>tmobile</folder>
  <filename>img000242</filename>
  <path>LogoDataset\tmobile\img000242.jpg</path>
  <source>
    <database>Unknown</database>
  </source>
  <size>
    <width>640</width>
    <height>447</height>
    <depth>3</depth>
  </size>
  <segmented>0</segmented>
  <object>
    <name>T-Mobile</name>
    <pose>Unspecified</pose>
    <truncated>0</truncated>
    <difficult>0</difficult>
    <bndbox>
      <xmin>5</xmin>
      <ymin>94</ymin>
      <xmax>626</xmax>
      <ymax>307</ymax>
    </bndbox>
  </object>
</annotation>
