<annotation>
  <folder>toyota</folder>
  <filename>img000082</filename>
  <path>LogoDataset\toyota\img000082.jpg</path>
  <source>
    <database>Unknown</database>
  </source>
  <size>
    <width>1000</width>
    <height>750</height>
    <depth>3</depth>
  </size>
  <segmented>0</segmented>
  <object>
    <name>toyota</name>
    <pose>Unspecified</pose>
    <truncated>0</truncated>
    <difficult>0</difficult>
    <bndbox>
      <xmin>572</xmin>
      <ymin>403</ymin>
      <xmax>605</xmax>
      <ymax>430</ymax>
    </bndbox>
  </object>
</annotation>
