<annotation>
  <folder>nescafe</folder>
  <filename>img000221</filename>
  <path>LogoDataset\nescafe\img000221.jpg</path>
  <source>
    <database>Unknown</database>
  </source>
  <size>
    <width>670</width>
    <height>446</height>
    <depth>3</depth>
  </size>
  <segmented>0</segmented>
  <object>
    <name>nescafe</name>
    <pose>Unspecified</pose>
    <truncated>0</truncated>
    <difficult>0</difficult>
    <bndbox>
      <xmin>417</xmin>
      <ymin>141</ymin>
      <xmax>512</xmax>
      <ymax>239</ymax>
    </bndbox>
  </object>
  <object>
    <name>Nestle</name>
    <pose>Unspecified</pose>
    <truncated>0</truncated>
    <difficult>0</difficult>
    <bndbox>
      <xmin>612</xmin>
      <ymin>425</ymin>
      <xmax>652</xmax>
      <ymax>437</ymax>
    </bndbox>
  </object>
  <object>
    <name>nescafe</name>
    <pose>Unspecified</pose>
    <truncated>0</truncated>
    <difficult>0</difficult>
    <bndbox>
      <xmin>18</xmin>
      <ymin>35</ymin>
      <xmax>313</xmax>
      <ymax>368</ymax>
    </bndbox>
  </object>
</annotation>
