<annotation>
  <folder>Pampers</folder>
  <filename>img000162</filename>
  <path>LogoDataset\Pampers\img000162.jpg</path>
  <source>
    <database>Unknown</database>
  </source>
  <size>
    <width>591</width>
    <height>299</height>
    <depth>3</depth>
  </size>
  <segmented>0</segmented>
  <object>
    <name>pampers</name>
    <pose>Unspecified</pose>
    <truncated>0</truncated>
    <difficult>0</difficult>
    <bndbox>
      <xmin>36</xmin>
      <ymin>102</ymin>
      <xmax>91</xmax>
      <ymax>136</ymax>
    </bndbox>
  </object>
  <object>
    <name>pampers</name>
    <pose>Unspecified</pose>
    <truncated>0</truncated>
    <difficult>0</difficult>
    <bndbox>
      <xmin>166</xmin>
      <ymin>96</ymin>
      <xmax>222</xmax>
      <ymax>132</ymax>
    </bndbox>
  </object>
  <object>
    <name>pampers</name>
    <pose>Unspecified</pose>
    <truncated>0</truncated>
    <difficult>0</difficult>
    <bndbox>
      <xmin>28</xmin>
      <ymin>28</ymin>
      <xmax>62</xmax>
      <ymax>46</ymax>
    </bndbox>
  </object>
  <object>
    <name>pampers</name>
    <pose>Unspecified</pose>
    <truncated>0</truncated>
    <difficult>0</difficult>
    <bndbox>
      <xmin>277</xmin>
      <ymin>107</ymin>
      <xmax>354</xmax>
      <ymax>150</ymax>
    </bndbox>
  </object>
  <object>
    <name>pampers</name>
    <pose>Unspecified</pose>
    <truncated>0</truncated>
    <difficult>0</difficult>
    <bndbox>
      <xmin>447</xmin>
      <ymin>102</ymin>
      <xmax>521</xmax>
      <ymax>147</ymax>
    </bndbox>
  </object>
  <object>
    <name>pampers</name>
    <pose>Unspecified</pose>
    <truncated>0</truncated>
    <difficult>0</difficult>
    <bndbox>
      <xmin>423</xmin>
      <ymin>13</ymin>
      <xmax>460</xmax>
      <ymax>35</ymax>
    </bndbox>
  </object>
  <object>
    <name>pampers</name>
    <pose>Unspecified</pose>
    <truncated>0</truncated>
    <difficult>0</difficult>
    <bndbox>
      <xmin>429</xmin>
      <ymin>65</ymin>
      <xmax>467</xmax>
      <ymax>89</ymax>
    </bndbox>
  </object>
  <object>
    <name>pampers-teilsichtbar</name>
    <pose>Unspecified</pose>
    <truncated>0</truncated>
    <difficult>0</difficult>
    <bndbox>
      <xmin>152</xmin>
      <ymin>249</ymin>
      <xmax>203</xmax>
      <ymax>264</ymax>
    </bndbox>
  </object>
  <object>
    <name>sesame street-teilsichtbar</name>
    <pose>Unspecified</pose>
    <truncated>0</truncated>
    <difficult>0</difficult>
    <bndbox>
      <xmin>402</xmin>
      <ymin>194</ymin>
      <xmax>419</xmax>
      <ymax>210</ymax>
    </bndbox>
  </object>
  <object>
    <name>sesame street-teilsichtbar</name>
    <pose>Unspecified</pose>
    <truncated>0</truncated>
    <difficult>0</difficult>
    <bndbox>
      <xmin>574</xmin>
      <ymin>186</ymin>
      <xmax>590</xmax>
      <ymax>203</ymax>
    </bndbox>
  </object>
  <object>
    <name>pampers-teilsichtbar</name>
    <pose>Unspecified</pose>
    <truncated>0</truncated>
    <difficult>0</difficult>
    <bndbox>
      <xmin>382</xmin>
      <ymin>83</ymin>
      <xmax>415</xmax>
      <ymax>95</ymax>
    </bndbox>
  </object>
</annotation>
