<annotation>
  <folder>coca-cola</folder>
  <filename>img000777</filename>
  <path>LogoDataset\coca-cola\img000777.jpg</path>
  <source>
    <database>Unknown</database>
  </source>
  <size>
    <width>630</width>
    <height>397</height>
    <depth>3</depth>
  </size>
  <segmented>0</segmented>
  <object>
    <name>coca-cola</name>
    <pose>Unspecified</pose>
    <truncated>0</truncated>
    <difficult>0</difficult>
    <bndbox>
      <xmin>11</xmin>
      <ymin>138</ymin>
      <xmax>66</xmax>
      <ymax>159</ymax>
    </bndbox>
  </object>
  <object>
    <name>coca-cola</name>
    <pose>Unspecified</pose>
    <truncated>0</truncated>
    <difficult>0</difficult>
    <bndbox>
      <xmin>397</xmin>
      <ymin>38</ymin>
      <xmax>630</xmax>
      <ymax>173</ymax>
    </bndbox>
  </object>
</annotation>
