<annotation>
  <folder>pepsi</folder>
  <filename>img000021</filename>
  <path>LogoDataset\pepsi\img000021.jpg</path>
  <source>
    <database>Unknown</database>
  </source>
  <size>
    <width>1890</width>
    <height>1264</height>
    <depth>3</depth>
  </size>
  <segmented>0</segmented>
  <object>
    <name>pepsi-logo</name>
    <pose>Unspecified</pose>
    <truncated>0</truncated>
    <difficult>0</difficult>
    <bndbox>
      <xmin>981</xmin>
      <ymin>422</ymin>
      <xmax>1057</xmax>
      <ymax>497</ymax>
    </bndbox>
  </object>
  <object>
    <name>pepsi-schrift1</name>
    <pose>Unspecified</pose>
    <truncated>0</truncated>
    <difficult>0</difficult>
    <bndbox>
      <xmin>947</xmin>
      <ymin>532</ymin>
      <xmax>1082</xmax>
      <ymax>567</ymax>
    </bndbox>
  </object>
  <object>
    <name>pepsi-schrift1</name>
    <pose>Unspecified</pose>
    <truncated>0</truncated>
    <difficult>0</difficult>
    <bndbox>
      <xmin>527</xmin>
      <ymin>1097</ymin>
      <xmax>877</xmax>
      <ymax>1221</ymax>
    </bndbox>
  </object>
  <object>
    <name>pepsi-logo</name>
    <pose>Unspecified</pose>
    <truncated>0</truncated>
    <difficult>0</difficult>
    <bndbox>
      <xmin>440</xmin>
      <ymin>1084</ymin>
      <xmax>527</xmax>
      <ymax>1258</ymax>
    </bndbox>
  </object>
  <object>
    <name>pepsi-logo</name>
    <pose>Unspecified</pose>
    <truncated>0</truncated>
    <difficult>0</difficult>
    <bndbox>
      <xmin>1662</xmin>
      <ymin>998</ymin>
      <xmax>1831</xmax>
      <ymax>1162</ymax>
    </bndbox>
  </object>
  <object>
    <name>pepsi-schrift1</name>
    <pose>Unspecified</pose>
    <truncated>0</truncated>
    <difficult>0</difficult>
    <bndbox>
      <xmin>1637</xmin>
      <ymin>1171</ymin>
      <xmax>1850</xmax>
      <ymax>1226</ymax>
    </bndbox>
  </object>
</annotation>
