<annotation>
  <folder>accenture</folder>
  <filename>img000091</filename>
  <path>H:\imagedataset1\accenture\img000091.jpg</path>
  <source>
    <database>Unknown</database>
  </source>
  <size>
    <width>500</width>
    <height>707</height>
    <depth>3</depth>
  </size>
  <segmented>0</segmented>
  <object>
    <name>accenture</name>
    <pose>Unspecified</pose>
    <truncated>0</truncated>
    <difficult>0</difficult>
    <bndbox>
      <xmin>29</xmin>
      <ymin>32</ymin>
      <xmax>143</xmax>
      <ymax>67</ymax>
    </bndbox>
  </object>
</annotation>
