<annotation>
  <folder>frito lays</folder>
  <filename>img000149</filename>
  <path>LogoDataset\frito lays\img000149.jpg</path>
  <source>
    <database>Unknown</database>
  </source>
  <size>
    <width>304</width>
    <height>203</height>
    <depth>3</depth>
  </size>
  <segmented>0</segmented>
  <object>
    <name>FritoLay</name>
    <pose>Unspecified</pose>
    <truncated>0</truncated>
    <difficult>0</difficult>
    <bndbox>
      <xmin>85</xmin>
      <ymin>87</ymin>
      <xmax>139</xmax>
      <ymax>132</ymax>
    </bndbox>
  </object>
  <object>
    <name>FritoLay</name>
    <pose>Unspecified</pose>
    <truncated>0</truncated>
    <difficult>0</difficult>
    <bndbox>
      <xmin>182</xmin>
      <ymin>117</ymin>
      <xmax>207</xmax>
      <ymax>137</ymax>
    </bndbox>
  </object>
  <object>
    <name>FritoLay</name>
    <pose>Unspecified</pose>
    <truncated>0</truncated>
    <difficult>0</difficult>
    <bndbox>
      <xmin>253</xmin>
      <ymin>29</ymin>
      <xmax>285</xmax>
      <ymax>46</ymax>
    </bndbox>
  </object>
  <object>
    <name>FritoLay-teilsichtbar</name>
    <pose>Unspecified</pose>
    <truncated>0</truncated>
    <difficult>0</difficult>
    <bndbox>
      <xmin>286</xmin>
      <ymin>132</ymin>
      <xmax>304</xmax>
      <ymax>151</ymax>
    </bndbox>
  </object>
</annotation>
