<annotation>
  <folder>FedEx</folder>
  <filename>img000241</filename>
  <path>LogoDataset\FedEx\img000241.jpg</path>
  <source>
    <database>Unknown</database>
  </source>
  <size>
    <width>700</width>
    <height>300</height>
    <depth>3</depth>
  </size>
  <segmented>0</segmented>
  <object>
    <name>FedEx</name>
    <pose>Unspecified</pose>
    <truncated>0</truncated>
    <difficult>0</difficult>
    <bndbox>
      <xmin>438</xmin>
      <ymin>79</ymin>
      <xmax>542</xmax>
      <ymax>167</ymax>
    </bndbox>
  </object>
  <object>
    <name>FedEx</name>
    <pose>Unspecified</pose>
    <truncated>0</truncated>
    <difficult>0</difficult>
    <bndbox>
      <xmin>582</xmin>
      <ymin>103</ymin>
      <xmax>694</xmax>
      <ymax>143</ymax>
    </bndbox>
  </object>
  <object>
    <name>FedEx-teilsichtbar</name>
    <pose>Unspecified</pose>
    <truncated>0</truncated>
    <difficult>0</difficult>
    <bndbox>
      <xmin>1</xmin>
      <ymin>63</ymin>
      <xmax>136</xmax>
      <ymax>130</ymax>
    </bndbox>
  </object>
  <object>
    <name>FedEx</name>
    <pose>Unspecified</pose>
    <truncated>0</truncated>
    <difficult>0</difficult>
    <bndbox>
      <xmin>306</xmin>
      <ymin>81</ymin>
      <xmax>324</xmax>
      <ymax>88</ymax>
    </bndbox>
  </object>
</annotation>
