<annotation>
  <folder>FedEx</folder>
  <filename>img000227</filename>
  <path>LogoDataset\FedEx\img000227.jpg</path>
  <source>
    <database>Unknown</database>
  </source>
  <size>
    <width>595</width>
    <height>335</height>
    <depth>3</depth>
  </size>
  <segmented>0</segmented>
  <object>
    <name>FedEx</name>
    <pose>Unspecified</pose>
    <truncated>0</truncated>
    <difficult>0</difficult>
    <bndbox>
      <xmin>116</xmin>
      <ymin>169</ymin>
      <xmax>151</xmax>
      <ymax>189</ymax>
    </bndbox>
  </object>
  <object>
    <name>FedEx</name>
    <pose>Unspecified</pose>
    <truncated>0</truncated>
    <difficult>0</difficult>
    <bndbox>
      <xmin>275</xmin>
      <ymin>206</ymin>
      <xmax>299</xmax>
      <ymax>221</ymax>
    </bndbox>
  </object>
  <object>
    <name>FedEx</name>
    <pose>Unspecified</pose>
    <truncated>0</truncated>
    <difficult>0</difficult>
    <bndbox>
      <xmin>393</xmin>
      <ymin>142</ymin>
      <xmax>464</xmax>
      <ymax>185</ymax>
    </bndbox>
  </object>
</annotation>
