<annotation>
  <folder>FedEx</folder>
  <filename>img000258</filename>
  <path>LogoDataset\FedEx\img000258.jpg</path>
  <source>
    <database>Unknown</database>
  </source>
  <size>
    <width>815</width>
    <height>300</height>
    <depth>3</depth>
  </size>
  <segmented>0</segmented>
  <object>
    <name>FedEx</name>
    <pose>Unspecified</pose>
    <truncated>0</truncated>
    <difficult>0</difficult>
    <bndbox>
      <xmin>244</xmin>
      <ymin>144</ymin>
      <xmax>347</xmax>
      <ymax>204</ymax>
    </bndbox>
  </object>
  <object>
    <name>FedEx</name>
    <pose>Unspecified</pose>
    <truncated>0</truncated>
    <difficult>0</difficult>
    <bndbox>
      <xmin>614</xmin>
      <ymin>207</ymin>
      <xmax>768</xmax>
      <ymax>256</ymax>
    </bndbox>
  </object>
  <object>
    <name>FedEx-teilsichtbar</name>
    <pose>Unspecified</pose>
    <truncated>0</truncated>
    <difficult>0</difficult>
    <bndbox>
      <xmin>439</xmin>
      <ymin>199</ymin>
      <xmax>455</xmax>
      <ymax>212</ymax>
    </bndbox>
  </object>
</annotation>
