<annotation>
  <folder>H&amp;M</folder>
  <filename>img000290</filename>
  <path>LogoDataset\H&amp;M\img000290.jpg</path>
  <source>
    <database>Unknown</database>
  </source>
  <size>
    <width>600</width>
    <height>450</height>
    <depth>3</depth>
  </size>
  <segmented>0</segmented>
  <object>
    <name>h&amp;m</name>
    <pose>Unspecified</pose>
    <truncated>0</truncated>
    <difficult>0</difficult>
    <bndbox>
      <xmin>86</xmin>
      <ymin>132</ymin>
      <xmax>119</xmax>
      <ymax>166</ymax>
    </bndbox>
  </object>
  <object>
    <name>h&amp;m</name>
    <pose>Unspecified</pose>
    <truncated>0</truncated>
    <difficult>0</difficult>
    <bndbox>
      <xmin>446</xmin>
      <ymin>141</ymin>
      <xmax>566</xmax>
      <ymax>224</ymax>
    </bndbox>
  </object>
</annotation>
