<annotation>
  <folder>H&amp;M</folder>
  <filename>img000307</filename>
  <path>LogoDataset\H&amp;M\img000307.jpg</path>
  <source>
    <database>Unknown</database>
  </source>
  <size>
    <width>600</width>
    <height>450</height>
    <depth>3</depth>
  </size>
  <segmented>0</segmented>
  <object>
    <name>h&amp;m</name>
    <pose>Unspecified</pose>
    <truncated>0</truncated>
    <difficult>0</difficult>
    <bndbox>
      <xmin>309</xmin>
      <ymin>278</ymin>
      <xmax>346</xmax>
      <ymax>305</ymax>
    </bndbox>
  </object>
  <object>
    <name>h&amp;m-teilsichtbar</name>
    <pose>Unspecified</pose>
    <truncated>0</truncated>
    <difficult>0</difficult>
    <bndbox>
      <xmin>83</xmin>
      <ymin>266</ymin>
      <xmax>107</xmax>
      <ymax>287</ymax>
    </bndbox>
  </object>
  <object>
    <name>h&amp;m</name>
    <pose>Unspecified</pose>
    <truncated>0</truncated>
    <difficult>0</difficult>
    <bndbox>
      <xmin>111</xmin>
      <ymin>307</ymin>
      <xmax>123</xmax>
      <ymax>316</ymax>
    </bndbox>
  </object>
  <object>
    <name>h&amp;m</name>
    <pose>Unspecified</pose>
    <truncated>0</truncated>
    <difficult>0</difficult>
    <bndbox>
      <xmin>515</xmin>
      <ymin>303</ymin>
      <xmax>527</xmax>
      <ymax>313</ymax>
    </bndbox>
  </object>
</annotation>
