<annotation>
  <folder>audi</folder>
  <filename>img000075</filename>
  <path>LogoDataset\audi\img000075.jpg</path>
  <source>
    <database>Unknown</database>
  </source>
  <size>
    <width>800</width>
    <height>414</height>
    <depth>3</depth>
  </size>
  <segmented>0</segmented>
  <object>
    <name>audi-logo</name>
    <pose>Unspecified</pose>
    <truncated>0</truncated>
    <difficult>0</difficult>
    <bndbox>
      <xmin>35</xmin>
      <ymin>239</ymin>
      <xmax>53</xmax>
      <ymax>260</ymax>
    </bndbox>
  </object>
  <object>
    <name>audi-schriftzug</name>
    <pose>Unspecified</pose>
    <truncated>0</truncated>
    <difficult>0</difficult>
    <bndbox>
      <xmin>281</xmin>
      <ymin>194</ymin>
      <xmax>315</xmax>
      <ymax>216</ymax>
    </bndbox>
  </object>
  <object>
    <name>VW</name>
    <pose>Unspecified</pose>
    <truncated>0</truncated>
    <difficult>0</difficult>
    <bndbox>
      <xmin>725</xmin>
      <ymin>246</ymin>
      <xmax>744</xmax>
      <ymax>268</ymax>
    </bndbox>
  </object>
</annotation>
