<annotation>
  <folder>wells fargo</folder>
  <filename>img000126</filename>
  <path>LogoDataset\wells fargo\img000126.jpg</path>
  <source>
    <database>Unknown</database>
  </source>
  <size>
    <width>992</width>
    <height>558</height>
    <depth>3</depth>
  </size>
  <segmented>0</segmented>
  <object>
    <name>WellsFargo</name>
    <pose>Unspecified</pose>
    <truncated>0</truncated>
    <difficult>0</difficult>
    <bndbox>
      <xmin>398</xmin>
      <ymin>49</ymin>
      <xmax>600</xmax>
      <ymax>139</ymax>
    </bndbox>
  </object>
</annotation>
