<annotation>
  <folder>adidas</folder>
  <filename>img000288</filename>
  <path>LogoDataset\adidas\img000288.jpg</path>
  <source>
    <database>Unknown</database>
  </source>
  <size>
    <width>750</width>
    <height>500</height>
    <depth>3</depth>
  </size>
  <segmented>0</segmented>
  <object>
    <name>adidas4-teilsichtbar</name>
    <pose>Unspecified</pose>
    <truncated>0</truncated>
    <difficult>0</difficult>
    <bndbox>
      <xmin>487</xmin>
      <ymin>168</ymin>
      <xmax>529</xmax>
      <ymax>185</ymax>
    </bndbox>
  </object>
  <object>
    <name>adidas4</name>
    <pose>Unspecified</pose>
    <truncated>0</truncated>
    <difficult>0</difficult>
    <bndbox>
      <xmin>195</xmin>
      <ymin>110</ymin>
      <xmax>239</xmax>
      <ymax>140</ymax>
    </bndbox>
  </object>
  <object>
    <name>adidas4</name>
    <pose>Unspecified</pose>
    <truncated>0</truncated>
    <difficult>0</difficult>
    <bndbox>
      <xmin>141</xmin>
      <ymin>300</ymin>
      <xmax>162</xmax>
      <ymax>315</ymax>
    </bndbox>
  </object>
</annotation>
