<annotation>
  <folder>budweiser</folder>
  <filename>img000236</filename>
  <path>LogoDataset\budweiser\img000236.jpg</path>
  <source>
    <database>Unknown</database>
  </source>
  <size>
    <width>800</width>
    <height>556</height>
    <depth>3</depth>
  </size>
  <segmented>0</segmented>
  <object>
    <name>Budweiser-schriftzug</name>
    <pose>Unspecified</pose>
    <truncated>0</truncated>
    <difficult>0</difficult>
    <bndbox>
      <xmin>612</xmin>
      <ymin>25</ymin>
      <xmax>684</xmax>
      <ymax>551</ymax>
    </bndbox>
  </object>
  <object>
    <name>Budweiser-schriftzug-teilsichtbar</name>
    <pose>Unspecified</pose>
    <truncated>0</truncated>
    <difficult>0</difficult>
    <bndbox>
      <xmin>1</xmin>
      <ymin>187</ymin>
      <xmax>134</xmax>
      <ymax>266</ymax>
    </bndbox>
  </object>
  <object>
    <name>Budweiser-schriftzug-teilsichtbar</name>
    <pose>Unspecified</pose>
    <truncated>0</truncated>
    <difficult>0</difficult>
    <bndbox>
      <xmin>382</xmin>
      <ymin>195</ymin>
      <xmax>423</xmax>
      <ymax>232</ymax>
    </bndbox>
  </object>
</annotation>
