<annotation>
  <folder>esso</folder>
  <filename>img000200</filename>
  <path>LogoDataset\esso\img000200.jpg</path>
  <source>
    <database>Unknown</database>
  </source>
  <size>
    <width>890</width>
    <height>480</height>
    <depth>3</depth>
  </size>
  <segmented>0</segmented>
  <object>
    <name>esso-logo</name>
    <pose>Unspecified</pose>
    <truncated>0</truncated>
    <difficult>0</difficult>
    <bndbox>
      <xmin>745</xmin>
      <ymin>40</ymin>
      <xmax>810</xmax>
      <ymax>87</ymax>
    </bndbox>
  </object>
  <object>
    <name>mobil</name>
    <pose>Unspecified</pose>
    <truncated>0</truncated>
    <difficult>0</difficult>
    <bndbox>
      <xmin>751</xmin>
      <ymin>96</ymin>
      <xmax>796</xmax>
      <ymax>120</ymax>
    </bndbox>
  </object>
  <object>
    <name>esso-schriftzug-teilsichtbar</name>
    <pose>Unspecified</pose>
    <truncated>0</truncated>
    <difficult>0</difficult>
    <bndbox>
      <xmin>703</xmin>
      <ymin>286</ymin>
      <xmax>758</xmax>
      <ymax>310</ymax>
    </bndbox>
  </object>
</annotation>
