<annotation>
  <folder>rolex</folder>
  <filename>img000096</filename>
  <path>LogoDataset\rolex\img000096.jpg</path>
  <source>
    <database>Unknown</database>
  </source>
  <size>
    <width>860</width>
    <height>701</height>
    <depth>3</depth>
  </size>
  <segmented>0</segmented>
  <object>
    <name>ROLEX</name>
    <pose>Unspecified</pose>
    <truncated>0</truncated>
    <difficult>0</difficult>
    <bndbox>
      <xmin>352</xmin>
      <ymin>218</ymin>
      <xmax>418</xmax>
      <ymax>277</ymax>
    </bndbox>
  </object>
  <object>
    <name>ROLEX-Krone</name>
    <pose>Unspecified</pose>
    <truncated>0</truncated>
    <difficult>0</difficult>
    <bndbox>
      <xmin>352</xmin>
      <ymin>217</ymin>
      <xmax>381</xmax>
      <ymax>244</ymax>
    </bndbox>
  </object>
</annotation>
