<annotation>
  <folder>aldi</folder>
  <filename>img000112</filename>
  <path>LogoDataset\aldi\img000112.jpg</path>
  <source>
    <database>Unknown</database>
  </source>
  <size>
    <width>576</width>
    <height>384</height>
    <depth>3</depth>
  </size>
  <segmented>0</segmented>
  <object>
    <name>aldi</name>
    <pose>Unspecified</pose>
    <truncated>0</truncated>
    <difficult>0</difficult>
    <bndbox>
      <xmin>234</xmin>
      <ymin>228</ymin>
      <xmax>268</xmax>
      <ymax>293</ymax>
    </bndbox>
  </object>
  <object>
    <name>aldi-teilsichtbar</name>
    <pose>Unspecified</pose>
    <truncated>0</truncated>
    <difficult>0</difficult>
    <bndbox>
      <xmin>224</xmin>
      <ymin>211</ymin>
      <xmax>239</xmax>
      <ymax>266</ymax>
    </bndbox>
  </object>
  <object>
    <name>aldi-teilsichtbar</name>
    <pose>Unspecified</pose>
    <truncated>0</truncated>
    <difficult>0</difficult>
    <bndbox>
      <xmin>275</xmin>
      <ymin>242</ymin>
      <xmax>310</xmax>
      <ymax>315</ymax>
    </bndbox>
  </object>
  <object>
    <name>aldi-teilsichtbar</name>
    <pose>Unspecified</pose>
    <truncated>0</truncated>
    <difficult>0</difficult>
    <bndbox>
      <xmin>312</xmin>
      <ymin>297</ymin>
      <xmax>345</xmax>
      <ymax>352</ymax>
    </bndbox>
  </object>
</annotation>
