<annotation>
  <folder>aldi</folder>
  <filename>img000168</filename>
  <path>LogoDataset\aldi\img000168.jpg</path>
  <source>
    <database>Unknown</database>
  </source>
  <size>
    <width>1770</width>
    <height>1180</height>
    <depth>3</depth>
  </size>
  <segmented>0</segmented>
  <object>
    <name>aldi</name>
    <pose>Unspecified</pose>
    <truncated>0</truncated>
    <difficult>0</difficult>
    <bndbox>
      <xmin>1081</xmin>
      <ymin>210</ymin>
      <xmax>1202</xmax>
      <ymax>434</ymax>
    </bndbox>
  </object>
  <object>
    <name>aldi-teilsichtbar</name>
    <pose>Unspecified</pose>
    <truncated>0</truncated>
    <difficult>0</difficult>
    <bndbox>
      <xmin>884</xmin>
      <ymin>673</ymin>
      <xmax>905</xmax>
      <ymax>705</ymax>
    </bndbox>
  </object>
</annotation>
