<annotation>
  <folder>cartier</folder>
  <filename>img000091</filename>
  <path>LogoDataset\cartier\img000091.jpg</path>
  <source>
    <database>Unknown</database>
  </source>
  <size>
    <width>860</width>
    <height>693</height>
    <depth>3</depth>
  </size>
  <segmented>0</segmented>
  <object>
    <name>cartier</name>
    <pose>Unspecified</pose>
    <truncated>0</truncated>
    <difficult>0</difficult>
    <bndbox>
      <xmin>369</xmin>
      <ymin>243</ymin>
      <xmax>471</xmax>
      <ymax>293</ymax>
    </bndbox>
  </object>
</annotation>
